llm_mcp/__init__.py
llm_mcp/ablation.py
llm_mcp/analysis.py
llm_mcp/server.py
llm_mcp/training.py
llm_mcp/visualization.py
llm_mcp/models/__init__.py
llm_mcp/models/gpt.py
llm_mcp/models/mamba.py
scicomp_llm_mcp-0.1.6.dist-info/METADATA
scicomp_llm_mcp-0.1.6.dist-info/WHEEL
scicomp_llm_mcp-0.1.6.dist-info/entry_points.txt
scicomp_llm_mcp-0.1.6.dist-info/RECORD
