Metadata-Version: 2.4
Name: scicomp-llm-mcp
Version: 0.1.6
Summary: MCP server for LLM training, fine-tuning, and experimentation
Project-URL: Homepage, https://github.com/andylbrummer/math-mcp
Project-URL: Documentation, https://andylbrummer.github.io/math-mcp/api/llm-mcp
Project-URL: Repository, https://github.com/andylbrummer/math-mcp
Author-email: Andy Brummer <andy@example.com>
License-Expression: MIT
Keywords: gpt,language-model,llm,mamba,mcp,model-context-protocol,training
Classifier: Development Status :: 4 - Beta
Classifier: Intended Audience :: Developers
Classifier: Intended Audience :: Science/Research
Classifier: License :: OSI Approved :: MIT License
Classifier: Programming Language :: Python :: 3
Classifier: Programming Language :: Python :: 3.11
Classifier: Programming Language :: Python :: 3.12
Classifier: Topic :: Scientific/Engineering :: Artificial Intelligence
Requires-Python: >=3.11
Requires-Dist: datasets>=2.14.0
Requires-Dist: mcp>=1.0.0
Requires-Dist: numpy>=1.26.0
Requires-Dist: scicomp-compute-core>=0.1.6
Requires-Dist: scicomp-mcp-common>=0.1.6
Requires-Dist: sentencepiece>=0.1.99
Requires-Dist: tiktoken>=0.5.0
Requires-Dist: torch>=2.1.0
Requires-Dist: transformers>=4.35.0
